{
    "dataset": {
        "N": 200,
        "data_folder": "Toy_laplacian_N200",
        "densities": [
            1,
            1,
            1,
            1,
            1
        ],
        "g_parameters": {
            "brstlg": 1,
            "elements_list": [
                8,
                13,
                14,
                12,
                26,
                29,
                31,
                72,
                71,
                62,
                60,
                92,
                20
            ]
        },
        "model": "Toy",
        "model_parameters": {
            "db_name": "simple_xrays_threshold.json",
            "e_offset": 0.208,
            "e_scale": 0.01,
            "e_size": 50,
            "params_dict": {
                "c": 25,
                "k": 5
            },
            "seed": 1
        },
        "phases_parameters": [
            {},
            {},
            {},
            {},
            {}
        ],
        "seeds_range": 10,
        "weights_parameters": {
            "shape_2D": [
                15,
                15
            ],
            "weight_type": "laplacian"
        }
    },
    "experiment": {
        "dataset": "dataset_Toy.json",
        "estimator": "NMF",
        "filename": "NMF_results",
        "hyperparameters": {
            "debug": 1,
            "epsilon_reg": 1.0,
            "init": "warn",
            "max_iter": 2000,
            "mu": 0.0,
            "n_components": 5,
            "random_state": 1,
            "tol": 0.0001
        }
    },
    "results": {
        "angles": [
            [
                3.072089992655723,
                7.3447403299895155,
                9.427592048368314,
                8.619981730634358,
                11.222494898405603
            ]
        ],
        "mse": [
            7.183774793867996,
            7.376285052164706,
            7.413693704560872,
            9.977861393697516,
            65.81699621797996
        ]
    },
    "samples": [
        "/Users/nati/SDSC/Projects/MLATEM/SNMF_EDXS/generated_datasets/Toy_laplacian_N200/sample_3.npz"
    ]
}